{
  "root": {
    "BREADCRUMBS:browse": "LT",

    "PAGE_ACTION:jump:title": "Jump to LT by the document no",
    "PAGE_ACTION:jump:placeholder": "Document no",
    "PAGE_ACTION:printDocument": "Print document",

    "PANEL:TITLE:details": "Fixed asset decommission document details",
    "PANEL:TITLE:attachments": "Attachments",
    "PANEL:TITLE:stages": "Stages",
    "PANEL:TITLE:addForm": "Fixed asset decommission document add form",
    "PANEL:TITLE:editForm": "Fixed asset decommission document edit form",

    "FORM:ACTION:add": "Add a new LT document",
    "FORM:ACTION:edit": "Save changes",
    "FORM:ACTION:print": "Printable version",
    "FORM:ACTION:verify": "Verify",
    "FORM:ACTION:acceptOwner": "Accept",
    "FORM:ACTION:acceptDepartment": "Accept",
    "FORM:ACTION:acceptFinance": "Accept",
    "FORM:ACTION:record": "Accept",
    "FORM:ACTION:finished": "Finish",
    "FORM:add:mergeInventoryNo": "Inventory no of the merged asset",
    "FORM:add:mergeLineSymbol": "Line symbol",
    "FORM:add:mergeType": "Is the merge full or partial?",
    "FORM:add:mergeNotes": "Notes",
    "FORM:add:mergeNotes:placeholder": "What % of the total asset?",
    "FORM:add:otherNotes": "Notes",
    "FORM:edit:verifyNotes": "Notes",
    "FORM:edit:verifyNotes:placeholder": "Factory number, build year, other...",
    "FORM:edit:attachment:old": "Current file:",
    "FORM:edit:attachment:new": "New file:",
    "FORM:edit:attachment:empty": "no file was attached.",
    "FORM:edit:attachment:help": "Select a new file only if you want to override the existing one.",
    "FORM:stage:protocol": "{kind, select, scrap{Scrapping<br>protocol} merge{Asset<br>merge<br>protocol} sale{Sale<br>protocol<br>} other{Other<br>protocol}}",
    "FORM:stage:acceptOwner": "Owner<br>acceptance",
    "FORM:stage:acceptDepartment": "Department<br>director<br>acceptance",
    "FORM:stage:acceptFinance": "Financial<br>director<br>acceptance",

    "details:stage:acceptOwner": "Owner<br>acceptance",
    "details:stage:acceptDepartment": "Department director<br>acceptance",
    "details:stage:acceptFinance": "Financial director<br>acceptance",

    "PROPERTY:stage": "Stage",
    "PROPERTY:kind": "Decommission kind",
    "PROPERTY:no": "Document no",
    "PROPERTY:date": "Document date",
    "PROPERTY:inventoryNo": "Inventory no",
    "PROPERTY:assetName": "Asset name",
    "PROPERTY:usageDestination": "Usage destination",
    "PROPERTY:applicant": "Applicant",
    "PROPERTY:cause": "Cause",
    "PROPERTY:initialValue": "Initial value",
    "PROPERTY:deprecationValue": "Deprecation value (fiscal)",
    "PROPERTY:netValue": "Net value (fiscal)",
    "PROPERTY:economicDeprecationValue": "Deprecation value (economic)",
    "PROPERTY:economicNetValue": "Net value (economic)",
    "PROPERTY:verifyNotes": "Notes (verification)",
    "PROPERTY:mergeInventoryNo": "Inventory no (merged asset)",
    "PROPERTY:mergeLineSymbol": "Line symbol (merged asset)",
    "PROPERTY:mergeType": "Merge type",
    "PROPERTY:mergeNotes": "Notes (merged asset)",
    "PROPERTY:buyerName": "Buyer's name",
    "PROPERTY:buyerAddress": "Buyer's address",
    "PROPERTY:saleValue": "Sale value",
    "PROPERTY:otherNotes": "Notes (other)",
    "PROPERTY:sapNo": "SAP no",
    "PROPERTY:accountingNo": "Accounting no",
    "PROPERTY:attachment": "Attachment",
    "PROPERTY:comment": "Comment",

    "kind:scrap": "Scrapping",
    "kind:merge": "Creation of a new fixed asset",
    "kind:sale": "Resale",
    "kind:other": "Other",
    "kind:short:scrap": "Scrapping",
    "kind:short:merge": "New asset",
    "kind:short:sale": "Resale",
    "kind:short:other": "Other",

    "mergeType:full": "Full",
    "mergeType:partial": "Partial",

    "stage:created": "Created",
    "stage:updated": "Updated",
    "stage:protocol": "Protocol",
    "stage:verify": "Verification",
    "stage:acceptOwner": "Owner acceptance",
    "stage:acceptDepartment": "Department director acceptance",
    "stage:acceptFinance": "Financial director acceptance",
    "stage:record": "Recording",
    "stage:finished": "Decommissioned",

    "filter:stage": "Stage",
    "filter:kind": "Kind",
    "filter:sapNo": "SAP no",
    "filter:assetName": "Asset name",
    "filter:inventoryNo": "Inventory no",
    "filter:limit": "Limit",

    "list:assetName": "Asset name",

    "changes:created": "<i>added a new LT document</i>",

    "print:document:title": "LT document"
  },
  "pl": true
}
